
{
    "author": [
        "Vertyco"
    ],
    "description": "Get Xbox player data using xbox API",
    "disabled" : false,
    "end_user_data_statement" : "This cog uses the xbl.io API",
    "hidden": false,
    "install_msg": "Thank you for installing! Use `[p]help XTools` for more info.",
    "min_bot_version" : "3.4.0",
    "min_python_version" : [3, 8, 1],
    "permissions" : ["embed_links"],
    "required_cogs" : {},
    "requirements" : [],
    "short": "Get gamertag info.",
    "tags" : ["fun", "tools", "utility"],
    "type": "COG"
}